setup.py
qflow/__init__.py
qflow/__main__.py
qflow/archive.py
qflow/archive_backend.py
qflow/archive_backend_test.py
qflow/archive_test.py
qflow/default_topic_map.py
qflow/reader.py
qflow/reader_test.py
qflow/simple_queue.py
qflow/simple_queue_test.py
qflow/subscriber.py
qflow/topic_map.py
qflow/topic_map_test.py
qflow/topic_map_util.py
qflow/topic_record.py
qflow/topic_record_test.py
qflow/util.py
qflow.egg-info/PKG-INFO
qflow.egg-info/SOURCES.txt
qflow.egg-info/dependency_links.txt
qflow.egg-info/entry_points.txt
qflow.egg-info/requires.txt
qflow.egg-info/top_level.txt