Metadata-Version: 1.0
Name: qflow
Version: 0.0.2
Summary: qflow package for personal use
Home-page: https://github.com/guoxiaoyong/qflow
Author: Guo Xiaoyong
Author-email: guo.xiaoyong@gmail.com
License: UNKNOWN
Platform: UNKNOWN
